tubedreams/__init__.py
tubedreams/tdparser.py
tubedreams/tubedreams.py
tubedreams/version.py
tubedreams-0.3.0.data/scripts/tubedreams
tubedreams-0.3.0.dist-info/METADATA
tubedreams-0.3.0.dist-info/RECORD
tubedreams-0.3.0.dist-info/WHEEL
tubedreams-0.3.0.dist-info/top_level.txt
