Metadata-Version: 2.1
Name: tubedreams
Version: 0.3.0
Summary: create dream-sequences from your video browsing history
Home-page: https://github.com/hdbhdb/tubedreams
Author: Hudson Bailey
Author-email: hudsondiggsbailey@gmail.com
License: MIT
Platform: UNKNOWN
Classifier: Programming Language :: Python :: 3
Classifier: Operating System :: OS Independent
Requires-Dist: sox (>=1.3.3)
Requires-Dist: youtube-dl (>=2018.5.18)
Requires-Dist: ez-setup (>=0.9)
Requires-Dist: moviepy (>=0.2.3.5)
